vkostyanetsky/cliutils/__init__.py
vkostyanetsky/cliutils/menu.py
vkostyanetsky/cliutils/prompt.py
vkostyanetsky/cliutils/version.py
vkostyanetsky.cliutils-0.2.0.dist-info/LICENSE
vkostyanetsky.cliutils-0.2.0.dist-info/METADATA
vkostyanetsky.cliutils-0.2.0.dist-info/WHEEL
vkostyanetsky.cliutils-0.2.0.dist-info/top_level.txt
vkostyanetsky.cliutils-0.2.0.dist-info/RECORD
