Metadata-Version: 2.1
Name: vkostyanetsky.cliutils
Version: 0.2.0
Summary: A tiny library that makes CLI apps development a bit faster.
Home-page: https://github.com/vkostyanetsky/CLIUtils
Author: Vlad Kostyanetsky
Author-email: vlad@kostyanetsky.me
License: MIT
Keywords: cli console menu progressbar
Classifier: Development Status :: 5 - Production/Stable
Classifier: Environment :: Console
Classifier: Topic :: Software Development :: Libraries :: Python Modules
Classifier: License :: OSI Approved :: MIT License
Classifier: Operating System :: POSIX
Classifier: Programming Language :: Python :: 3.10
Requires-Python: >=3.7
License-File: LICENSE
